shapeandshare/fingerprint/dataset/__init__.py
shapeandshare/fingerprint/dataset/contracts/__init__.py
shapeandshare/fingerprint/dataset/contracts/missing_hashes_error.py
shapeandshare/fingerprint/dataset/contracts/source_type.py
shapeandshare/fingerprint/dataset/contracts/dtos/__init__.py
shapeandshare/fingerprint/dataset/contracts/dtos/base_model.py
shapeandshare/fingerprint/dataset/contracts/dtos/data_set.py
shapeandshare/fingerprint/dataset/contracts/dtos/file_record.py
shapeandshare/fingerprint/dataset/contracts/dtos/hash_metadata.py
shapeandshare/fingerprint/dataset/utils/__init__.py
shapeandshare/fingerprint/dataset/utils/hash.py
shapeandshare_fingerprint_dataset-0.4.2.dist-info/LICENSE
shapeandshare_fingerprint_dataset-0.4.2.dist-info/METADATA
shapeandshare_fingerprint_dataset-0.4.2.dist-info/WHEEL
shapeandshare_fingerprint_dataset-0.4.2.dist-info/top_level.txt
shapeandshare_fingerprint_dataset-0.4.2.dist-info/RECORD
