Metadata-Version: 2.1
Name: shapeandshare-fingerprint-dataset
Version: 0.4.2
Summary: Generates file hash reports
Author: Joshua C. Burt
Author-email: joshburt@shapeandshare.com
License: MIT
Platform: UNKNOWN
Requires-Python: >=3.9
License-File: LICENSE
Requires-Dist: pydantic (>=1.9.0)
Requires-Dist: tqdm (>=4.63.0)
Requires-Dist: pandas (>=1.4.1)
